{
  "АЕЦ": 1821.23,
  "Кондензационни ТЕЦ": 577.8,
  "Топлофикационни ТЕЦ": 145.76,
  "Заводски ТЕЦ": 83.74,
  "ВЕЦ": 340.2,
  "Малки ВЕЦ": 328.85,
  "ВяЕЦ": 18.73,
  "ФЕЦ": 0.0,
  "Био ЕЦ": 17.48,
  "Товар на РБ": 2934.89,
  "pumps_mw": 0.0,
  "ССЕЕ_mw": 29.0,
  "ССЕЕ_state": "discharging",
  "RO_mw": -552.98,
  "SR_mw": -165.20000000000002,
  "MK_mw": -147.18,
  "GR_mw": 170.25,
  "TR_mw": 266.8,
  "gen_total_mw": 3333.8,
  "net_import_mw": -428.3,
  "load_mw": 2934.9,
  "batt_charge_mw": 17.4,
  "batt_discharge_mw": 46.4,
  "raw_gen_api": [
    [
      "АЕЦ 53,88%",
      1821.23
    ],
    [
      "Кондензационни ТЕЦ 17,09%",
      577.8
    ],
    [
      "Топлофикационни ТЕЦ 4,31%",
      145.76
    ],
    [
      "Заводски ТЕЦ 2,48%",
      83.74
    ],
    [
      "ВЕЦ 10,06%",
      340.2
    ],
    [
      "Малки ВЕЦ 9,73%",
      328.85
    ],
    [
      "ВяЕЦ 0,55%",
      18.73
    ],
    [
      "ФЕЦ 0,00%",
      0
    ],
    [
      "Био ЕЦ 0,52%",
      17.48
    ],
    [
      "ССЕБ - разреждане",
      "46.36"
    ],
    [
      "Товар на РБ",
      2934.89
    ],
    [
      "ССЕБ - зареждане",
      "17.36"
    ],
    [
      "Помпи",
      "0.00"
    ]
  ],
  "timestamp_utc": "2026-06-16T22:20:03Z",
  "date_bg": "2026-06-17"
}