{
  "АЕЦ": 1972.68,
  "Кондензационни ТЕЦ": 514.43,
  "Топлофикационни ТЕЦ": 134.94,
  "Заводски ТЕЦ": 127.88,
  "ВЕЦ": 112.84,
  "Малки ВЕЦ": 195.61,
  "ВяЕЦ": 50.86,
  "ФЕЦ": 2505.02,
  "Био ЕЦ": 12.63,
  "Товар на РБ": 4229.78,
  "pumps_mw": 0.0,
  "ССЕЕ_mw": -335.61,
  "ССЕЕ_state": "charging",
  "RO_mw": -966.25,
  "SR_mw": -413.4,
  "MK_mw": -24.58,
  "GR_mw": 351.42999999999995,
  "TR_mw": -4.69,
  "gen_total_mw": 5626.9,
  "net_import_mw": -1057.5,
  "load_mw": 4229.8,
  "batt_charge_mw": 412.0,
  "batt_discharge_mw": 76.4,
  "raw_gen_api": [
    [
      "АЕЦ 34,59%",
      1972.68
    ],
    [
      "Кондензационни ТЕЦ 9,02%",
      514.43
    ],
    [
      "Топлофикационни ТЕЦ 2,37%",
      134.94
    ],
    [
      "Заводски ТЕЦ 2,24%",
      127.88
    ],
    [
      "ВЕЦ 1,98%",
      112.84
    ],
    [
      "Малки ВЕЦ 3,43%",
      195.61
    ],
    [
      "ВяЕЦ 0,89%",
      50.86
    ],
    [
      "ФЕЦ 43,92%",
      2505.02
    ],
    [
      "Био ЕЦ 0,22%",
      12.63
    ],
    [
      "ССЕБ - разреждане",
      "76.41"
    ],
    [
      "Товар на РБ",
      4229.78
    ],
    [
      "ССЕБ - зареждане",
      "412.02"
    ],
    [
      "Помпи",
      "0.00"
    ]
  ],
  "timestamp_utc": "2026-06-22T13:20:03Z",
  "date_bg": "2026-06-22"
}