{
  "АЕЦ": 980.98,
  "Кондензационни ТЕЦ": 530.11,
  "Топлофикационни ТЕЦ": 128.5,
  "Заводски ТЕЦ": 98.38,
  "ВЕЦ": 528.02,
  "Малки ВЕЦ": 375.12,
  "ВяЕЦ": 41.16,
  "ФЕЦ": 2520.73,
  "Био ЕЦ": 12.73,
  "Товар на РБ": 3653.88,
  "pumps_mw": 0.0,
  "ССЕЕ_mw": -353.24,
  "ССЕЕ_state": "charging",
  "RO_mw": -825.46,
  "SR_mw": -521.1899999999999,
  "MK_mw": -106.84,
  "GR_mw": 85.06,
  "TR_mw": 162.64,
  "gen_total_mw": 5215.7,
  "net_import_mw": -1205.8,
  "load_mw": 3653.9,
  "batt_charge_mw": 374.8,
  "batt_discharge_mw": 21.6,
  "raw_gen_api": [
    [
      "АЕЦ 18,73%",
      980.98
    ],
    [
      "Кондензационни ТЕЦ 10,12%",
      530.11
    ],
    [
      "Топлофикационни ТЕЦ 2,45%",
      128.5
    ],
    [
      "Заводски ТЕЦ 1,88%",
      98.38
    ],
    [
      "ВЕЦ 10,08%",
      528.02
    ],
    [
      "Малки ВЕЦ 7,16%",
      375.12
    ],
    [
      "ВяЕЦ 0,79%",
      41.16
    ],
    [
      "ФЕЦ 48,13%",
      2520.73
    ],
    [
      "Био ЕЦ 0,24%",
      12.73
    ],
    [
      "ССЕБ - разреждане",
      "21.59"
    ],
    [
      "Товар на РБ",
      3653.88
    ],
    [
      "ССЕБ - зареждане",
      "374.83"
    ],
    [
      "Помпи",
      "0.00"
    ]
  ],
  "timestamp_utc": "2026-06-09T14:05:03Z",
  "date_bg": "2026-06-09"
}