{
  "АЕЦ": 983.69,
  "Кондензационни ТЕЦ": 401.73,
  "Топлофикационни ТЕЦ": 154.75,
  "Заводски ТЕЦ": 131.09,
  "ВЕЦ": 1172.24,
  "Малки ВЕЦ": 389.71,
  "ВяЕЦ": 52.78,
  "ФЕЦ": 583.22,
  "Био ЕЦ": 13.13,
  "Товар на РБ": 3749.6,
  "pumps_mw": 0.0,
  "ССЕЕ_mw": 26.34,
  "ССЕЕ_state": "discharging",
  "RO_mw": -395.53999999999996,
  "SR_mw": 61.89,
  "MK_mw": -163.9,
  "GR_mw": -77.2,
  "TR_mw": 405.08,
  "gen_total_mw": 3882.3,
  "net_import_mw": -169.7,
  "load_mw": 3749.6,
  "batt_charge_mw": 5.9,
  "batt_discharge_mw": 32.3,
  "raw_gen_api": [
    [
      "АЕЦ 25,13%",
      983.69
    ],
    [
      "Кондензационни ТЕЦ 10,26%",
      401.73
    ],
    [
      "Топлофикационни ТЕЦ 3,95%",
      154.75
    ],
    [
      "Заводски ТЕЦ 3,35%",
      131.09
    ],
    [
      "ВЕЦ 29,95%",
      1172.24
    ],
    [
      "Малки ВЕЦ 9,96%",
      389.71
    ],
    [
      "ВяЕЦ 1,35%",
      52.78
    ],
    [
      "ФЕЦ 14,90%",
      583.22
    ],
    [
      "Био ЕЦ 0,34%",
      13.13
    ],
    [
      "ССЕБ - разреждане",
      "32.27"
    ],
    [
      "Товар на РБ",
      3749.6
    ],
    [
      "ССЕБ - зареждане",
      "5.93"
    ],
    [
      "Помпи",
      "0.00"
    ]
  ],
  "timestamp_utc": "2026-06-06T16:25:03Z",
  "date_bg": "2026-06-06"
}