{
  "АЕЦ": 984.45,
  "Кондензационни ТЕЦ": 371.7,
  "Топлофикационни ТЕЦ": 160.06,
  "Заводски ТЕЦ": 129.33,
  "ВЕЦ": 650.32,
  "Малки ВЕЦ": 373.84,
  "ВяЕЦ": 22.03,
  "ФЕЦ": 2167.85,
  "Био ЕЦ": 17.68,
  "Товар на РБ": 3482.98,
  "pumps_mw": 0.0,
  "ССЕЕ_mw": -216.66,
  "ССЕЕ_state": "charging",
  "RO_mw": -1174.3,
  "SR_mw": -379.04,
  "MK_mw": -137.89999999999998,
  "GR_mw": 218.23000000000002,
  "TR_mw": 291.40999999999997,
  "gen_total_mw": 4877.3,
  "net_import_mw": -1181.6,
  "load_mw": 3483.0,
  "batt_charge_mw": 219.6,
  "batt_discharge_mw": 2.9,
  "raw_gen_api": [
    [
      "АЕЦ 20,17%",
      984.45
    ],
    [
      "Кондензационни ТЕЦ 7,62%",
      371.7
    ],
    [
      "Топлофикационни ТЕЦ 3,28%",
      160.06
    ],
    [
      "Заводски ТЕЦ 2,65%",
      129.33
    ],
    [
      "ВЕЦ 13,33%",
      650.32
    ],
    [
      "Малки ВЕЦ 7,66%",
      373.84
    ],
    [
      "ВяЕЦ 0,45%",
      22.03
    ],
    [
      "ФЕЦ 44,42%",
      2167.85
    ],
    [
      "Био ЕЦ 0,36%",
      17.68
    ],
    [
      "ССЕБ - разреждане",
      "2.94"
    ],
    [
      "Товар на РБ",
      3482.98
    ],
    [
      "ССЕБ - зареждане",
      "219.60"
    ],
    [
      "Помпи",
      "0.00"
    ]
  ],
  "timestamp_utc": "2026-06-05T05:55:02Z",
  "date_bg": "2026-06-05"
}