{
  "АЕЦ": 980.22,
  "Кондензационни ТЕЦ": 523.94,
  "Топлофикационни ТЕЦ": 156.65,
  "Заводски ТЕЦ": 118.5,
  "ВЕЦ": 1339.86,
  "Малки ВЕЦ": 391.61,
  "ВяЕЦ": 282.89,
  "ФЕЦ": 0.0,
  "Био ЕЦ": 11.83,
  "Товар на РБ": 3385.42,
  "pumps_mw": 0.0,
  "ССЕЕ_mw": 1855.78,
  "ССЕЕ_state": "discharging",
  "RO_mw": -1349.3400000000001,
  "SR_mw": -471.90999999999997,
  "MK_mw": -392.07,
  "GR_mw": -129.74,
  "TR_mw": 58.89,
  "gen_total_mw": 3805.5,
  "net_import_mw": -2284.2,
  "load_mw": 3385.4,
  "batt_charge_mw": 28.4,
  "batt_discharge_mw": 1884.1,
  "raw_gen_api": [
    [
      "АЕЦ 17,23%",
      980.22
    ],
    [
      "Кондензационни ТЕЦ 9,21%",
      523.94
    ],
    [
      "Топлофикационни ТЕЦ 2,75%",
      156.65
    ],
    [
      "Заводски ТЕЦ 2,08%",
      118.5
    ],
    [
      "ВЕЦ 23,55%",
      1339.86
    ],
    [
      "Малки ВЕЦ 6,88%",
      391.61
    ],
    [
      "ВяЕЦ 4,97%",
      282.89
    ],
    [
      "ФЕЦ 0,00%",
      0
    ],
    [
      "Био ЕЦ 0,21%",
      11.83
    ],
    [
      "ССЕБ - разреждане",
      "1884.14"
    ],
    [
      "Товар на РБ",
      3385.42
    ],
    [
      "ССЕБ - зареждане",
      "28.36"
    ],
    [
      "Помпи",
      "0.00"
    ]
  ],
  "timestamp_utc": "2026-06-12T17:50:03Z",
  "date_bg": "2026-06-12"
}