{
  "АЕЦ": 1978.4,
  "Кондензационни ТЕЦ": 370.03,
  "Топлофикационни ТЕЦ": 145.55,
  "Заводски ТЕЦ": 101.52,
  "ВЕЦ": 484.51,
  "Малки ВЕЦ": 246.73,
  "ВяЕЦ": 59.84,
  "ФЕЦ": 2155.21,
  "Био ЕЦ": 12.49,
  "Товар на РБ": 3971.05,
  "pumps_mw": 0.0,
  "ССЕЕ_mw": -59.08,
  "ССЕЕ_state": "charging",
  "RO_mw": -1640.8400000000001,
  "SR_mw": -494.84,
  "MK_mw": -109.07,
  "GR_mw": 325.12,
  "TR_mw": 388.47,
  "gen_total_mw": 5554.3,
  "net_import_mw": -1531.2,
  "load_mw": 3971.1,
  "batt_charge_mw": 60.4,
  "batt_discharge_mw": 1.3,
  "raw_gen_api": [
    [
      "АЕЦ 35,61%",
      1978.4
    ],
    [
      "Кондензационни ТЕЦ 6,66%",
      370.03
    ],
    [
      "Топлофикационни ТЕЦ 2,62%",
      145.55
    ],
    [
      "Заводски ТЕЦ 1,83%",
      101.52
    ],
    [
      "ВЕЦ 8,72%",
      484.51
    ],
    [
      "Малки ВЕЦ 4,44%",
      246.73
    ],
    [
      "ВяЕЦ 1,08%",
      59.84
    ],
    [
      "ФЕЦ 38,79%",
      2155.21
    ],
    [
      "Био ЕЦ 0,22%",
      12.49
    ],
    [
      "ССЕБ - разреждане",
      "1.33"
    ],
    [
      "Товар на РБ",
      3971.05
    ],
    [
      "ССЕБ - зареждане",
      "60.41"
    ],
    [
      "Помпи",
      "0.00"
    ]
  ],
  "timestamp_utc": "2026-06-18T15:00:03Z",
  "date_bg": "2026-06-18"
}