{
  "АЕЦ": 1973.06,
  "Кондензационни ТЕЦ": 499.68,
  "Топлофикационни ТЕЦ": 142.92,
  "Заводски ТЕЦ": 102.0,
  "ВЕЦ": 1008.54,
  "Малки ВЕЦ": 346.64,
  "ВяЕЦ": 42.2,
  "ФЕЦ": 0.0,
  "Био ЕЦ": 12.55,
  "Товар на РБ": 3747.17,
  "pumps_mw": 0.0,
  "ССЕЕ_mw": 2489.34,
  "ССЕЕ_state": "discharging",
  "RO_mw": -2586.02,
  "SR_mw": -390.9,
  "MK_mw": -262.78,
  "GR_mw": 107.12,
  "TR_mw": 277.53,
  "gen_total_mw": 4127.6,
  "net_import_mw": -2855.1,
  "load_mw": 3747.2,
  "batt_charge_mw": 0.4,
  "batt_discharge_mw": 2489.7,
  "raw_gen_api": [
    [
      "АЕЦ 29,82%",
      1973.06
    ],
    [
      "Кондензационни ТЕЦ 7,55%",
      499.68
    ],
    [
      "Топлофикационни ТЕЦ 2,16%",
      142.92
    ],
    [
      "Заводски ТЕЦ 1,54%",
      102
    ],
    [
      "ВЕЦ 15,24%",
      1008.54
    ],
    [
      "Малки ВЕЦ 5,24%",
      346.64
    ],
    [
      "ВяЕЦ 0,64%",
      42.2
    ],
    [
      "ФЕЦ 0,00%",
      0
    ],
    [
      "Био ЕЦ 0,19%",
      12.55
    ],
    [
      "ССЕБ - разреждане",
      "2489.73"
    ],
    [
      "Товар на РБ",
      3747.17
    ],
    [
      "ССЕБ - зареждане",
      "0.39"
    ],
    [
      "Помпи",
      "0.00"
    ]
  ],
  "timestamp_utc": "2026-06-23T18:00:02Z",
  "date_bg": "2026-06-23"
}