{
  "АЕЦ": 991.7,
  "Кондензационни ТЕЦ": 505.04,
  "Топлофикационни ТЕЦ": 170.01,
  "Заводски ТЕЦ": 125.77,
  "ВЕЦ": 10.02,
  "Малки ВЕЦ": 252.55,
  "ВяЕЦ": 455.56,
  "ФЕЦ": 2901.84,
  "Био ЕЦ": 13.14,
  "Товар на РБ": 3800.77,
  "ССЕЕ_mw": -1478.74,
  "ССЕЕ_state": "charging",
  "RO_mw": -666.38,
  "SR_mw": -534.03,
  "MK_mw": 131.03,
  "GR_mw": 560.63,
  "TR_mw": 335.15,
  "gen_total_mw": 5425.6,
  "net_import_mw": -173.6,
  "load_mw": 3800.8,
  "batt_charge_mw": 1478.7,
  "batt_discharge_mw": 28.9,
  "timestamp_utc": "2026-05-20T10:10:03Z",
  "date_bg": "2026-05-20"
}