{
  "АЕЦ": 993.22,
  "Кондензационни ТЕЦ": 736.51,
  "Топлофикационни ТЕЦ": 179.76,
  "Заводски ТЕЦ": 123.45,
  "ВЕЦ": 82.64,
  "Малки ВЕЦ": 351.96,
  "ВяЕЦ": 301.32,
  "ФЕЦ": 0.0,
  "Био ЕЦ": 18.09,
  "Товар на РБ": 3034.97,
  "ССЕЕ_mw": -8.36,
  "ССЕЕ_state": "charging",
  "RO_mw": -730.83,
  "SR_mw": -88.56,
  "MK_mw": 15.309999999999995,
  "GR_mw": 565.71,
  "TR_mw": 484.80999999999995,
  "gen_total_mw": 2786.9,
  "net_import_mw": 246.4,
  "load_mw": 3035.0,
  "batt_charge_mw": 8.4,
  "batt_discharge_mw": 10.2,
  "timestamp_utc": "2026-05-18T22:30:03Z",
  "date_bg": "2026-05-19"
}