{
  "АЕЦ": 984.07,
  "Кондензационни ТЕЦ": 413.27,
  "Топлофикационни ТЕЦ": 162.67,
  "Заводски ТЕЦ": 131.11,
  "ВЕЦ": 754.31,
  "Малки ВЕЦ": 369.48,
  "ВяЕЦ": 68.37,
  "ФЕЦ": 0.0,
  "Био ЕЦ": 16.79,
  "Товар на РБ": 3292.0,
  "ССЕЕ_mw": -9.77,
  "ССЕЕ_state": "charging",
  "RO_mw": -1031.01,
  "SR_mw": -217.53,
  "MK_mw": -65.3,
  "GR_mw": 437.7,
  "TR_mw": 330.37,
  "gen_total_mw": 2900.1,
  "net_import_mw": -545.8,
  "load_mw": 3292.0,
  "batt_charge_mw": 9.8,
  "batt_discharge_mw": 920.8,
  "timestamp_utc": "2026-06-02T20:25:02Z",
  "date_bg": "2026-06-02"
}