{
  "АЕЦ": 979.07,
  "Кондензационни ТЕЦ": 566.14,
  "Топлофикационни ТЕЦ": 151.51,
  "Заводски ТЕЦ": 118.38,
  "ВЕЦ": 886.59,
  "Малки ВЕЦ": 379.15,
  "ВяЕЦ": 134.91,
  "ФЕЦ": 160.1,
  "Био ЕЦ": 16.07,
  "Товар на РБ": 3148.17,
  "pumps_mw": 0.0,
  "ССЕЕ_mw": -38.48,
  "ССЕЕ_state": "charging",
  "RO_mw": -430.78,
  "SR_mw": 26.119999999999997,
  "MK_mw": -140.29,
  "GR_mw": 79.76,
  "TR_mw": 252.97,
  "gen_total_mw": 3391.9,
  "net_import_mw": -212.2,
  "load_mw": 3148.2,
  "batt_charge_mw": 41.2,
  "batt_discharge_mw": 2.7,
  "raw_gen_api": [
    [
      "АЕЦ 28,84%",
      979.07
    ],
    [
      "Кондензационни ТЕЦ 16,68%",
      566.14
    ],
    [
      "Топлофикационни ТЕЦ 4,46%",
      151.51
    ],
    [
      "Заводски ТЕЦ 3,49%",
      118.38
    ],
    [
      "ВЕЦ 26,12%",
      886.59
    ],
    [
      "Малки ВЕЦ 11,17%",
      379.15
    ],
    [
      "ВяЕЦ 3,97%",
      134.91
    ],
    [
      "ФЕЦ 4,72%",
      160.1
    ],
    [
      "Био ЕЦ 0,47%",
      16.07
    ],
    [
      "ССЕБ - разреждане",
      "2.68"
    ],
    [
      "Товар на РБ",
      3148.17
    ],
    [
      "ССЕБ - зареждане",
      "41.16"
    ],
    [
      "Помпи",
      "0.00"
    ]
  ],
  "timestamp_utc": "2026-06-12T03:10:03Z",
  "date_bg": "2026-06-12"
}