{
  "АЕЦ": 1987.21,
  "Кондензационни ТЕЦ": 369.4,
  "Топлофикационни ТЕЦ": 145.77,
  "Заводски ТЕЦ": 100.76,
  "ВЕЦ": 678.49,
  "Малки ВЕЦ": 279.82,
  "ВяЕЦ": 63.01,
  "ФЕЦ": 1435.36,
  "Био ЕЦ": 12.51,
  "Товар на РБ": 4134.11,
  "pumps_mw": 0.0,
  "ССЕЕ_mw": -29.24,
  "ССЕЕ_state": "charging",
  "RO_mw": -1134.8,
  "SR_mw": -271.97,
  "MK_mw": -97.97999999999999,
  "GR_mw": 306.75,
  "TR_mw": 259.08,
  "gen_total_mw": 5072.3,
  "net_import_mw": -938.9,
  "load_mw": 4134.1,
  "batt_charge_mw": 41.2,
  "batt_discharge_mw": 12.0,
  "raw_gen_api": [
    [
      "АЕЦ 39,09%",
      1987.21
    ],
    [
      "Кондензационни ТЕЦ 7,27%",
      369.4
    ],
    [
      "Топлофикационни ТЕЦ 2,87%",
      145.77
    ],
    [
      "Заводски ТЕЦ 1,98%",
      100.76
    ],
    [
      "ВЕЦ 13,34%",
      678.49
    ],
    [
      "Малки ВЕЦ 5,50%",
      279.82
    ],
    [
      "ВяЕЦ 1,24%",
      63.01
    ],
    [
      "ФЕЦ 28,23%",
      1435.36
    ],
    [
      "Био ЕЦ 0,25%",
      12.51
    ],
    [
      "ССЕБ - разреждане",
      "11.96"
    ],
    [
      "Товар на РБ",
      4134.11
    ],
    [
      "ССЕБ - зареждане",
      "41.20"
    ],
    [
      "Помпи",
      "0.00"
    ]
  ],
  "timestamp_utc": "2026-06-18T15:40:02Z",
  "date_bg": "2026-06-18"
}