{
  "АЕЦ": 976.78,
  "Кондензационни ТЕЦ": 524.31,
  "Топлофикационни ТЕЦ": 121.37,
  "Заводски ТЕЦ": 117.52,
  "ВЕЦ": 316.07,
  "Малки ВЕЦ": 194.72,
  "ВяЕЦ": 85.08,
  "ФЕЦ": 1232.76,
  "Био ЕЦ": 17.32,
  "Товар на РБ": 3857.4,
  "pumps_mw": 0.0,
  "ССЕЕ_mw": -42.7,
  "ССЕЕ_state": "charging",
  "RO_mw": 168.94,
  "SR_mw": 114.42999999999999,
  "MK_mw": -48.17,
  "GR_mw": -21.56,
  "TR_mw": 88.68,
  "gen_total_mw": 3585.9,
  "net_import_mw": 302.3,
  "load_mw": 3857.4,
  "batt_charge_mw": 45.8,
  "batt_discharge_mw": 3.1,
  "raw_gen_api": [
    [
      "АЕЦ 27,22%",
      976.78
    ],
    [
      "Кондензационни ТЕЦ 14,61%",
      524.31
    ],
    [
      "Топлофикационни ТЕЦ 3,38%",
      121.37
    ],
    [
      "Заводски ТЕЦ 3,27%",
      117.52
    ],
    [
      "ВЕЦ 8,81%",
      316.07
    ],
    [
      "Малки ВЕЦ 5,43%",
      194.72
    ],
    [
      "ВяЕЦ 2,37%",
      85.08
    ],
    [
      "ФЕЦ 34,35%",
      1232.76
    ],
    [
      "Био ЕЦ 0,48%",
      17.32
    ],
    [
      "ССЕБ - разреждане",
      "3.12"
    ],
    [
      "Товар на РБ",
      3857.4
    ],
    [
      "ССЕБ - зареждане",
      "45.82"
    ],
    [
      "Помпи",
      "0.00"
    ]
  ],
  "timestamp_utc": "2026-06-14T14:45:03Z",
  "date_bg": "2026-06-14"
}