{
  "АЕЦ": 1974.97,
  "Кондензационни ТЕЦ": 518.8,
  "Топлофикационни ТЕЦ": 134.88,
  "Заводски ТЕЦ": 102.81,
  "ВЕЦ": 11.98,
  "Малки ВЕЦ": 200.36,
  "ВяЕЦ": 17.0,
  "ФЕЦ": 3041.65,
  "Био ЕЦ": 12.42,
  "Товар на РБ": 3969.62,
  "pumps_mw": 53.44,
  "ССЕЕ_mw": -985.05,
  "ССЕЕ_state": "charging",
  "RO_mw": -583.94,
  "SR_mw": -434.65,
  "MK_mw": -213.55,
  "GR_mw": -49.75999999999999,
  "TR_mw": 259.81,
  "gen_total_mw": 6014.9,
  "net_import_mw": -1022.1,
  "load_mw": 3969.6,
  "batt_charge_mw": 1007.8,
  "batt_discharge_mw": 22.7,
  "raw_gen_api": [
    [
      "АЕЦ 32,71%",
      1974.97
    ],
    [
      "Кондензационни ТЕЦ 8,59%",
      518.8
    ],
    [
      "Топлофикационни ТЕЦ 2,23%",
      134.88
    ],
    [
      "Заводски ТЕЦ 1,70%",
      102.81
    ],
    [
      "ВЕЦ 0,20%",
      11.98
    ],
    [
      "Малки ВЕЦ 3,32%",
      200.36
    ],
    [
      "ВяЕЦ 0,28%",
      17
    ],
    [
      "ФЕЦ 50,38%",
      3041.65
    ],
    [
      "Био ЕЦ 0,21%",
      12.42
    ],
    [
      "ССЕБ - разреждане",
      "22.74"
    ],
    [
      "Товар на РБ",
      3969.62
    ],
    [
      "ССЕБ - зареждане",
      "1007.79"
    ],
    [
      "Помпи",
      "53.44"
    ]
  ],
  "timestamp_utc": "2026-06-24T12:40:03Z",
  "date_bg": "2026-06-24"
}