{
  "АЕЦ": 1974.59,
  "Кондензационни ТЕЦ": 521.37,
  "Топлофикационни ТЕЦ": 127.74,
  "Заводски ТЕЦ": 116.03,
  "ВЕЦ": 41.68,
  "Малки ВЕЦ": 223.03,
  "ВяЕЦ": 9.16,
  "ФЕЦ": 3059.73,
  "Био ЕЦ": 17.09,
  "Товар на РБ": 4267.78,
  "pumps_mw": 188.01,
  "ССЕЕ_mw": -762.71,
  "ССЕЕ_state": "charging",
  "RO_mw": -1328.9099999999999,
  "SR_mw": -356.84999999999997,
  "MK_mw": 102.98,
  "GR_mw": 506.5,
  "TR_mw": 186.47,
  "gen_total_mw": 6090.4,
  "net_import_mw": -889.8,
  "load_mw": 4267.8,
  "batt_charge_mw": 763.3,
  "batt_discharge_mw": 0.6,
  "raw_gen_api": [
    [
      "АЕЦ 32,41%",
      1974.59
    ],
    [
      "Кондензационни ТЕЦ 8,56%",
      521.37
    ],
    [
      "Топлофикационни ТЕЦ 2,10%",
      127.74
    ],
    [
      "Заводски ТЕЦ 1,90%",
      116.03
    ],
    [
      "ВЕЦ 0,68%",
      41.68
    ],
    [
      "Малки ВЕЦ 3,66%",
      223.03
    ],
    [
      "ВяЕЦ 0,15%",
      9.16
    ],
    [
      "ФЕЦ 50,21%",
      3059.73
    ],
    [
      "Био ЕЦ 0,28%",
      17.09
    ],
    [
      "ССЕБ - разреждане",
      "0.61"
    ],
    [
      "Товар на РБ",
      4267.78
    ],
    [
      "ССЕБ - зареждане",
      "763.32"
    ],
    [
      "Помпи",
      "188.01"
    ]
  ],
  "timestamp_utc": "2026-06-23T07:15:02Z",
  "date_bg": "2026-06-23"
}