{
  "АЕЦ": 991.32,
  "Кондензационни ТЕЦ": 505.29,
  "Топлофикационни ТЕЦ": 164.04,
  "Заводски ТЕЦ": 130.77,
  "ВЕЦ": 10.2,
  "Малки ВЕЦ": 288.27,
  "ВяЕЦ": 17.11,
  "ФЕЦ": 2828.06,
  "Био ЕЦ": 17.84,
  "Товар на РБ": 3770.74,
  "ССЕЕ_mw": -1623.2,
  "ССЕЕ_state": "charging",
  "RO_mw": 71.24,
  "SR_mw": -307.15999999999997,
  "MK_mw": 97.41,
  "GR_mw": 533,
  "TR_mw": 92.67,
  "gen_total_mw": 4952.9,
  "net_import_mw": 487.2,
  "load_mw": 3770.7,
  "batt_charge_mw": 1623.2,
  "batt_discharge_mw": 0.0,
  "timestamp_utc": "2026-05-27T11:25:03Z",
  "date_bg": "2026-05-27"
}