{
  "АЕЦ": 983.31,
  "Кондензационни ТЕЦ": 357.49,
  "Топлофикационни ТЕЦ": 172.44,
  "Заводски ТЕЦ": 136.51,
  "ВЕЦ": 701.91,
  "Малки ВЕЦ": 322.42,
  "ВяЕЦ": 135.61,
  "ФЕЦ": 2461.08,
  "Био ЕЦ": 15.96,
  "Товар на РБ": 3025.84,
  "ССЕЕ_mw": -18.52,
  "ССЕЕ_state": "charging",
  "RO_mw": -1414.03,
  "SR_mw": -723.0899999999999,
  "MK_mw": -198.08999999999997,
  "GR_mw": 44.120000000000005,
  "TR_mw": 58.21000000000001,
  "gen_total_mw": 5286.7,
  "net_import_mw": -2232.9,
  "load_mw": 3025.8,
  "batt_charge_mw": 18.5,
  "batt_discharge_mw": 0.0,
  "timestamp_utc": "2026-05-30T05:40:03Z",
  "date_bg": "2026-05-30"
}