{
  "АЕЦ": 990.94,
  "Кондензационни ТЕЦ": 560.56,
  "Топлофикационни ТЕЦ": 184.63,
  "Заводски ТЕЦ": 100.89,
  "ВЕЦ": 134.47,
  "Малки ВЕЦ": 323.09,
  "ВяЕЦ": 166.55,
  "ФЕЦ": 0.0,
  "Био ЕЦ": 17.92,
  "Товар на РБ": 2835.72,
  "ССЕЕ_mw": -1.21,
  "ССЕЕ_state": "charging",
  "RO_mw": -930.91,
  "SR_mw": 128.3,
  "MK_mw": 149.2,
  "GR_mw": 615.99,
  "TR_mw": 409.38,
  "gen_total_mw": 2479.1,
  "net_import_mw": 372.0,
  "load_mw": 2835.7,
  "batt_charge_mw": 1.2,
  "batt_discharge_mw": 0.0,
  "timestamp_utc": "2026-05-22T01:30:03Z",
  "date_bg": "2026-05-22"
}