{
  "АЕЦ": 973.35,
  "Кондензационни ТЕЦ": 533.91,
  "Топлофикационни ТЕЦ": 129.14,
  "Заводски ТЕЦ": 123.67,
  "ВЕЦ": 12.98,
  "Малки ВЕЦ": 195.13,
  "ВяЕЦ": 171.7,
  "ФЕЦ": 1546.83,
  "Био ЕЦ": 16.42,
  "Товар на РБ": 3824.4,
  "pumps_mw": 470.25,
  "ССЕЕ_mw": -1398.09,
  "ССЕЕ_state": "charging",
  "RO_mw": 1054.6499999999999,
  "SR_mw": 380.54,
  "MK_mw": 192.71,
  "GR_mw": 229.45999999999998,
  "TR_mw": 114.65,
  "gen_total_mw": 3703.1,
  "net_import_mw": 1972.0,
  "load_mw": 3824.4,
  "batt_charge_mw": 1424.6,
  "batt_discharge_mw": 26.5,
  "raw_gen_api": [
    [
      "АЕЦ 26,10%",
      973.35
    ],
    [
      "Кондензационни ТЕЦ 14,32%",
      533.91
    ],
    [
      "Топлофикационни ТЕЦ 3,46%",
      129.14
    ],
    [
      "Заводски ТЕЦ 3,32%",
      123.67
    ],
    [
      "ВЕЦ 0,35%",
      12.98
    ],
    [
      "Малки ВЕЦ 5,23%",
      195.13
    ],
    [
      "ВяЕЦ 4,60%",
      171.7
    ],
    [
      "ФЕЦ 41,47%",
      1546.83
    ],
    [
      "Био ЕЦ 0,44%",
      16.42
    ],
    [
      "ССЕБ - разреждане",
      "26.51"
    ],
    [
      "Товар на РБ",
      3824.4
    ],
    [
      "ССЕБ - зареждане",
      "1424.60"
    ],
    [
      "Помпи",
      "470.25"
    ]
  ],
  "timestamp_utc": "2026-06-13T09:05:03Z",
  "date_bg": "2026-06-13"
}