{
  "АЕЦ": 993.99,
  "Кондензационни ТЕЦ": 519.82,
  "Топлофикационни ТЕЦ": 168.45,
  "Заводски ТЕЦ": 131.6,
  "ВЕЦ": 58.03,
  "Малки ВЕЦ": 235.39,
  "ВяЕЦ": 32.6,
  "ФЕЦ": 2577.86,
  "Био ЕЦ": 17.29,
  "Товар на РБ": 3416.48,
  "ССЕЕ_mw": -1499.47,
  "ССЕЕ_state": "charging",
  "RO_mw": -238.08999999999997,
  "SR_mw": -416.93,
  "MK_mw": 81.28,
  "GR_mw": 527.93,
  "TR_mw": 142.09,
  "gen_total_mw": 4735.0,
  "net_import_mw": 96.3,
  "load_mw": 3416.5,
  "batt_charge_mw": 1499.5,
  "batt_discharge_mw": 0.0,
  "timestamp_utc": "2026-05-26T08:55:02Z",
  "date_bg": "2026-05-26"
}