{
  "АЕЦ": 991.32,
  "Кондензационни ТЕЦ": 565.07,
  "Топлофикационни ТЕЦ": 172.89,
  "Заводски ТЕЦ": 104.66,
  "ВЕЦ": 846.51,
  "Малки ВЕЦ": 382.85,
  "ВяЕЦ": 226.66,
  "ФЕЦ": 0.0,
  "Био ЕЦ": 17.46,
  "Товар на РБ": 3567.52,
  "ССЕЕ_mw": -0.37,
  "ССЕЕ_state": "charging",
  "RO_mw": -1721.1,
  "SR_mw": -372.86,
  "MK_mw": -48.03,
  "GR_mw": 510.88,
  "TR_mw": 471.62,
  "gen_total_mw": 3307.4,
  "net_import_mw": -1159.5,
  "load_mw": 3567.5,
  "batt_charge_mw": 0.4,
  "batt_discharge_mw": 1428.0,
  "timestamp_utc": "2026-05-23T20:15:03Z",
  "date_bg": "2026-05-23"
}