{
  "АЕЦ": 1506.43,
  "Кондензационни ТЕЦ": 590.03,
  "Топлофикационни ТЕЦ": 147.0,
  "Заводски ТЕЦ": 86.37,
  "ВЕЦ": 929.66,
  "Малки ВЕЦ": 346.32,
  "ВяЕЦ": 32.46,
  "ФЕЦ": 0.0,
  "Био ЕЦ": 17.66,
  "Товар на РБ": 3256.65,
  "pumps_mw": 0.0,
  "ССЕЕ_mw": 229.58,
  "ССЕЕ_state": "discharging",
  "RO_mw": -1128.68,
  "SR_mw": -238.63,
  "MK_mw": -161.69,
  "GR_mw": 331.27000000000004,
  "TR_mw": 506.78000000000003,
  "gen_total_mw": 3655.9,
  "net_import_mw": -691.0,
  "load_mw": 3256.7,
  "batt_charge_mw": 3.6,
  "batt_discharge_mw": 233.1,
  "raw_gen_api": [
    [
      "АЕЦ 38,73%",
      1506.43
    ],
    [
      "Кондензационни ТЕЦ 15,17%",
      590.03
    ],
    [
      "Топлофикационни ТЕЦ 3,78%",
      147
    ],
    [
      "Заводски ТЕЦ 2,22%",
      86.37
    ],
    [
      "ВЕЦ 23,90%",
      929.66
    ],
    [
      "Малки ВЕЦ 8,90%",
      346.32
    ],
    [
      "ВяЕЦ 0,83%",
      32.46
    ],
    [
      "ФЕЦ 0,00%",
      0
    ],
    [
      "Био ЕЦ 0,45%",
      17.66
    ],
    [
      "ССЕБ - разреждане",
      "233.14"
    ],
    [
      "Товар на РБ",
      3256.65
    ],
    [
      "ССЕБ - зареждане",
      "3.56"
    ],
    [
      "Помпи",
      "0.00"
    ]
  ],
  "timestamp_utc": "2026-06-15T21:25:03Z",
  "date_bg": "2026-06-16"
}