{
  "АЕЦ": 975.64,
  "Кондензационни ТЕЦ": 585.16,
  "Топлофикационни ТЕЦ": 151.76,
  "Заводски ТЕЦ": 117.85,
  "ВЕЦ": 997.98,
  "Малки ВЕЦ": 381.85,
  "ВяЕЦ": 106.3,
  "ФЕЦ": 563.39,
  "Био ЕЦ": 16.33,
  "Товар на РБ": 3458.45,
  "pumps_mw": 0.0,
  "ССЕЕ_mw": -51.81,
  "ССЕЕ_state": "charging",
  "RO_mw": -797.3,
  "SR_mw": -35.95,
  "MK_mw": -70.47999999999999,
  "GR_mw": 243.69000000000003,
  "TR_mw": 273.73,
  "gen_total_mw": 3896.3,
  "net_import_mw": -386.3,
  "load_mw": 3458.4,
  "batt_charge_mw": 68.1,
  "batt_discharge_mw": 16.3,
  "raw_gen_api": [
    [
      "АЕЦ 24,94%",
      975.64
    ],
    [
      "Кондензационни ТЕЦ 14,96%",
      585.16
    ],
    [
      "Топлофикационни ТЕЦ 3,88%",
      151.76
    ],
    [
      "Заводски ТЕЦ 3,01%",
      117.85
    ],
    [
      "ВЕЦ 25,51%",
      997.98
    ],
    [
      "Малки ВЕЦ 9,76%",
      381.85
    ],
    [
      "ВяЕЦ 2,72%",
      106.3
    ],
    [
      "ФЕЦ 14,40%",
      563.39
    ],
    [
      "Био ЕЦ 0,42%",
      16.33
    ],
    [
      "ССЕБ - разреждане",
      "16.32"
    ],
    [
      "Товар на РБ",
      3458.45
    ],
    [
      "ССЕБ - зареждане",
      "68.13"
    ],
    [
      "Помпи",
      "0.00"
    ]
  ],
  "timestamp_utc": "2026-06-12T04:20:03Z",
  "date_bg": "2026-06-12"
}