{
  "АЕЦ": 986.74,
  "Кондензационни ТЕЦ": 600.64,
  "Топлофикационни ТЕЦ": 188.41,
  "Заводски ТЕЦ": 132.94,
  "ВЕЦ": 1438.67,
  "Малки ВЕЦ": 388.01,
  "ВяЕЦ": 115.94,
  "ФЕЦ": 0.0,
  "Био ЕЦ": 16.56,
  "Товар на РБ": 3363.14,
  "ССЕЕ_mw": -0.24,
  "ССЕЕ_state": "charging",
  "RO_mw": -2089.41,
  "SR_mw": -401.88,
  "MK_mw": -262.17,
  "GR_mw": 235.76,
  "TR_mw": 394.73,
  "gen_total_mw": 3867.9,
  "net_import_mw": -2123.0,
  "load_mw": 3363.1,
  "batt_charge_mw": 0.2,
  "batt_discharge_mw": 1613.9,
  "timestamp_utc": "2026-05-31T19:00:02Z",
  "date_bg": "2026-05-31"
}