{
  "АЕЦ": 1913.17,
  "Кондензационни ТЕЦ": 451.85,
  "Топлофикационни ТЕЦ": 151.68,
  "Заводски ТЕЦ": 82.31,
  "ВЕЦ": 813.29,
  "Малки ВЕЦ": 355.59,
  "ВяЕЦ": 5.75,
  "ФЕЦ": 1009.8,
  "Био ЕЦ": 16.43,
  "Товар на РБ": 3526.4,
  "pumps_mw": 0.0,
  "ССЕЕ_mw": 46.69,
  "ССЕЕ_state": "discharging",
  "RO_mw": -968.71,
  "SR_mw": -266.68,
  "MK_mw": -277.89,
  "GR_mw": -66.89000000000001,
  "TR_mw": 226.51,
  "gen_total_mw": 4799.9,
  "net_import_mw": -1353.7,
  "load_mw": 3526.4,
  "batt_charge_mw": 14.8,
  "batt_discharge_mw": 61.5,
  "raw_gen_api": [
    [
      "АЕЦ 39,35%",
      1913.17
    ],
    [
      "Кондензационни ТЕЦ 9,29%",
      451.85
    ],
    [
      "Топлофикационни ТЕЦ 3,12%",
      151.68
    ],
    [
      "Заводски ТЕЦ 1,69%",
      82.31
    ],
    [
      "ВЕЦ 16,73%",
      813.29
    ],
    [
      "Малки ВЕЦ 7,31%",
      355.59
    ],
    [
      "ВяЕЦ 0,12%",
      5.75
    ],
    [
      "ФЕЦ 20,77%",
      1009.8
    ],
    [
      "Био ЕЦ 0,34%",
      16.43
    ],
    [
      "ССЕБ - разреждане",
      "61.50"
    ],
    [
      "Товар на РБ",
      3526.4
    ],
    [
      "ССЕБ - зареждане",
      "14.81"
    ],
    [
      "Помпи",
      "0.00"
    ]
  ],
  "timestamp_utc": "2026-06-17T04:30:03Z",
  "date_bg": "2026-06-17"
}