{
  "АЕЦ": 982.92,
  "Кондензационни ТЕЦ": 517.98,
  "Топлофикационни ТЕЦ": 153.87,
  "Заводски ТЕЦ": 100.71,
  "ВЕЦ": 940.0,
  "Малки ВЕЦ": 396.65,
  "ВяЕЦ": 2.72,
  "ФЕЦ": 193.21,
  "Био ЕЦ": 17.07,
  "Товар на РБ": 3151.95,
  "pumps_mw": 0.0,
  "ССЕЕ_mw": -4.59,
  "ССЕЕ_state": "charging",
  "RO_mw": -576.5699999999999,
  "SR_mw": -108.52,
  "MK_mw": -118.72,
  "GR_mw": 263.63,
  "TR_mw": 383.98,
  "gen_total_mw": 3305.1,
  "net_import_mw": -156.2,
  "load_mw": 3151.9,
  "batt_charge_mw": 7.6,
  "batt_discharge_mw": 3.0,
  "raw_gen_api": [
    [
      "АЕЦ 29,71%",
      982.92
    ],
    [
      "Кондензационни ТЕЦ 15,66%",
      517.98
    ],
    [
      "Топлофикационни ТЕЦ 4,65%",
      153.87
    ],
    [
      "Заводски ТЕЦ 3,04%",
      100.71
    ],
    [
      "ВЕЦ 28,41%",
      940
    ],
    [
      "Малки ВЕЦ 11,99%",
      396.65
    ],
    [
      "ВяЕЦ 0,08%",
      2.72
    ],
    [
      "ФЕЦ 5,84%",
      193.21
    ],
    [
      "Био ЕЦ 0,52%",
      17.07
    ],
    [
      "ССЕБ - разреждане",
      "3.04"
    ],
    [
      "Товар на РБ",
      3151.95
    ],
    [
      "ССЕБ - зареждане",
      "7.63"
    ],
    [
      "Помпи",
      "0.00"
    ]
  ],
  "timestamp_utc": "2026-06-09T03:15:02Z",
  "date_bg": "2026-06-09"
}