{
  "АЕЦ": 1980.69,
  "Кондензационни ТЕЦ": 367.13,
  "Топлофикационни ТЕЦ": 130.14,
  "Заводски ТЕЦ": 126.15,
  "ВЕЦ": 13.01,
  "Малки ВЕЦ": 177.42,
  "ВяЕЦ": 7.2,
  "ФЕЦ": 2191.2,
  "Био ЕЦ": 16.72,
  "Товар на РБ": 3952.6,
  "pumps_mw": 525.57,
  "ССЕЕ_mw": -1876.57,
  "ССЕЕ_state": "charging",
  "RO_mw": 346.05,
  "SR_mw": -53.01,
  "MK_mw": 209.85,
  "GR_mw": 548.6,
  "TR_mw": 287.21,
  "gen_total_mw": 5009.7,
  "net_import_mw": 1338.7,
  "load_mw": 3952.6,
  "batt_charge_mw": 1876.6,
  "batt_discharge_mw": 0.0,
  "raw_gen_api": [
    [
      "АЕЦ 39,54%",
      1980.69
    ],
    [
      "Кондензационни ТЕЦ 7,33%",
      367.13
    ],
    [
      "Топлофикационни ТЕЦ 2,60%",
      130.14
    ],
    [
      "Заводски ТЕЦ 2,52%",
      126.15
    ],
    [
      "ВЕЦ 0,26%",
      13.01
    ],
    [
      "Малки ВЕЦ 3,54%",
      177.42
    ],
    [
      "ВяЕЦ 0,14%",
      7.2
    ],
    [
      "ФЕЦ 43,74%",
      2191.2
    ],
    [
      "Био ЕЦ 0,33%",
      16.72
    ],
    [
      "ССЕБ - разреждане",
      "0.00"
    ],
    [
      "Товар на РБ",
      3952.6
    ],
    [
      "ССЕБ - зареждане",
      "1876.57"
    ],
    [
      "Помпи",
      "525.57"
    ]
  ],
  "timestamp_utc": "2026-06-20T09:10:02Z",
  "date_bg": "2026-06-20"
}