{
  "АЕЦ": 1979.16,
  "Кондензационни ТЕЦ": 379.26,
  "Топлофикационни ТЕЦ": 134.57,
  "Заводски ТЕЦ": 119.29,
  "ВЕЦ": 13.05,
  "Малки ВЕЦ": 200.12,
  "ВяЕЦ": 25.65,
  "ФЕЦ": 2716.57,
  "Био ЕЦ": 16.17,
  "Товар на РБ": 4049.53,
  "pumps_mw": 186.14,
  "ССЕЕ_mw": -587.27,
  "ССЕЕ_state": "charging",
  "RO_mw": -1000.23,
  "SR_mw": -364.82,
  "MK_mw": 15.97,
  "GR_mw": 262.52,
  "TR_mw": 334.08,
  "gen_total_mw": 5583.8,
  "net_import_mw": -752.5,
  "load_mw": 4049.5,
  "batt_charge_mw": 587.4,
  "batt_discharge_mw": 0.1,
  "raw_gen_api": [
    [
      "АЕЦ 35,44%",
      1979.16
    ],
    [
      "Кондензационни ТЕЦ 6,79%",
      379.26
    ],
    [
      "Топлофикационни ТЕЦ 2,41%",
      134.57
    ],
    [
      "Заводски ТЕЦ 2,14%",
      119.29
    ],
    [
      "ВЕЦ 0,23%",
      13.05
    ],
    [
      "Малки ВЕЦ 3,58%",
      200.12
    ],
    [
      "ВяЕЦ 0,46%",
      25.65
    ],
    [
      "ФЕЦ 48,65%",
      2716.57
    ],
    [
      "Био ЕЦ 0,29%",
      16.17
    ],
    [
      "ССЕБ - разреждане",
      "0.14"
    ],
    [
      "Товар на РБ",
      4049.53
    ],
    [
      "ССЕБ - зареждане",
      "587.41"
    ],
    [
      "Помпи",
      "186.14"
    ]
  ],
  "timestamp_utc": "2026-06-22T07:05:03Z",
  "date_bg": "2026-06-22"
}