{
  "АЕЦ": 983.69,
  "Кондензационни ТЕЦ": 372.44,
  "Топлофикационни ТЕЦ": 159.84,
  "Заводски ТЕЦ": 96.59,
  "ВЕЦ": 939.77,
  "Малки ВЕЦ": 391.09,
  "ВяЕЦ": 71.14,
  "ФЕЦ": 440.63,
  "Био ЕЦ": 16.7,
  "Товар на РБ": 3230.87,
  "pumps_mw": 0.0,
  "ССЕЕ_mw": 7.58,
  "ССЕЕ_state": "discharging",
  "RO_mw": -974.1800000000001,
  "SR_mw": -194.83,
  "MK_mw": -53.370000000000005,
  "GR_mw": 492.24,
  "TR_mw": 501.30999999999995,
  "gen_total_mw": 3471.9,
  "net_import_mw": -228.8,
  "load_mw": 3230.9,
  "batt_charge_mw": 4.6,
  "batt_discharge_mw": 12.2,
  "raw_gen_api": [
    [
      "АЕЦ 28,23%",
      983.69
    ],
    [
      "Кондензационни ТЕЦ 10,69%",
      372.44
    ],
    [
      "Топлофикационни ТЕЦ 4,59%",
      159.84
    ],
    [
      "Заводски ТЕЦ 2,77%",
      96.59
    ],
    [
      "ВЕЦ 26,97%",
      939.77
    ],
    [
      "Малки ВЕЦ 11,23%",
      391.09
    ],
    [
      "ВяЕЦ 2,04%",
      71.14
    ],
    [
      "ФЕЦ 12,65%",
      440.63
    ],
    [
      "Био ЕЦ 0,48%",
      16.7
    ],
    [
      "ССЕБ - разреждане",
      "12.18"
    ],
    [
      "Товар на РБ",
      3230.87
    ],
    [
      "ССЕБ - зареждане",
      "4.60"
    ],
    [
      "Помпи",
      "0.00"
    ]
  ],
  "timestamp_utc": "2026-06-08T03:45:03Z",
  "date_bg": "2026-06-08"
}