{
  "АЕЦ": 992.08,
  "Кондензационни ТЕЦ": 508.96,
  "Топлофикационни ТЕЦ": 164.54,
  "Заводски ТЕЦ": 130.09,
  "ВЕЦ": 11.91,
  "Малки ВЕЦ": 302.72,
  "ВяЕЦ": 27.84,
  "ФЕЦ": 2658.77,
  "Био ЕЦ": 17.84,
  "Товар на РБ": 3630.66,
  "ССЕЕ_mw": -1535.76,
  "ССЕЕ_state": "charging",
  "RO_mw": -131.28,
  "SR_mw": -393.57,
  "MK_mw": 87.28,
  "GR_mw": 551.99,
  "TR_mw": 229.05,
  "gen_total_mw": 4814.8,
  "net_import_mw": 343.5,
  "load_mw": 3630.7,
  "batt_charge_mw": 1535.8,
  "batt_discharge_mw": 0.0,
  "timestamp_utc": "2026-05-27T12:15:03Z",
  "date_bg": "2026-05-27"
}