{
  "АЕЦ": 1987.21,
  "Кондензационни ТЕЦ": 368.0,
  "Топлофикационни ТЕЦ": 137.19,
  "Заводски ТЕЦ": 95.6,
  "ВЕЦ": 14.07,
  "Малки ВЕЦ": 220.12,
  "ВяЕЦ": 99.31,
  "ФЕЦ": 2807.41,
  "Био ЕЦ": 12.61,
  "Товар на РБ": 4257.24,
  "pumps_mw": 522.58,
  "ССЕЕ_mw": -2030.33,
  "ССЕЕ_state": "charging",
  "RO_mw": 158.7,
  "SR_mw": -96.74000000000001,
  "MK_mw": 226.96,
  "GR_mw": 660.75,
  "TR_mw": 95.12,
  "gen_total_mw": 5741.5,
  "net_import_mw": 1044.8,
  "load_mw": 4257.2,
  "batt_charge_mw": 2030.4,
  "batt_discharge_mw": 0.1,
  "raw_gen_api": [
    [
      "АЕЦ 34,61%",
      1987.21
    ],
    [
      "Кондензационни ТЕЦ 6,41%",
      368
    ],
    [
      "Топлофикационни ТЕЦ 2,39%",
      137.19
    ],
    [
      "Заводски ТЕЦ 1,67%",
      95.6
    ],
    [
      "ВЕЦ 0,25%",
      14.07
    ],
    [
      "Малки ВЕЦ 3,83%",
      220.12
    ],
    [
      "ВяЕЦ 1,73%",
      99.31
    ],
    [
      "ФЕЦ 48,90%",
      2807.41
    ],
    [
      "Био ЕЦ 0,22%",
      12.61
    ],
    [
      "ССЕБ - разреждане",
      "0.10"
    ],
    [
      "Товар на РБ",
      4257.24
    ],
    [
      "ССЕБ - зареждане",
      "2030.43"
    ],
    [
      "Помпи",
      "522.58"
    ]
  ],
  "timestamp_utc": "2026-06-19T11:40:03Z",
  "date_bg": "2026-06-19"
}