{
  "АЕЦ": 1861.67,
  "Кондензационни ТЕЦ": 395.94,
  "Топлофикационни ТЕЦ": 151.44,
  "Заводски ТЕЦ": 80.39,
  "ВЕЦ": 326.88,
  "Малки ВЕЦ": 294.16,
  "ВяЕЦ": 17.86,
  "ФЕЦ": 0.0,
  "Био ЕЦ": 17.03,
  "Товар на РБ": 2848.02,
  "pumps_mw": 0.0,
  "ССЕЕ_mw": -10.38,
  "ССЕЕ_state": "charging",
  "RO_mw": -314.60999999999996,
  "SR_mw": -88.39,
  "MK_mw": -162.74,
  "GR_mw": 79.05999999999999,
  "TR_mw": 191.35,
  "gen_total_mw": 3145.4,
  "net_import_mw": -295.3,
  "load_mw": 2848.0,
  "batt_charge_mw": 12.7,
  "batt_discharge_mw": 2.3,
  "raw_gen_api": [
    [
      "АЕЦ 59,14%",
      1861.67
    ],
    [
      "Кондензационни ТЕЦ 12,58%",
      395.94
    ],
    [
      "Топлофикационни ТЕЦ 4,81%",
      151.44
    ],
    [
      "Заводски ТЕЦ 2,55%",
      80.39
    ],
    [
      "ВЕЦ 10,38%",
      326.88
    ],
    [
      "Малки ВЕЦ 9,35%",
      294.16
    ],
    [
      "ВяЕЦ 0,57%",
      17.86
    ],
    [
      "ФЕЦ 0,00%",
      0
    ],
    [
      "Био ЕЦ 0,54%",
      17.03
    ],
    [
      "ССЕБ - разреждане",
      "2.31"
    ],
    [
      "Товар на РБ",
      2848.02
    ],
    [
      "ССЕБ - зареждане",
      "12.69"
    ],
    [
      "Помпи",
      "0.00"
    ]
  ],
  "timestamp_utc": "2026-06-16T23:40:02Z",
  "date_bg": "2026-06-17"
}