{
  "АЕЦ": 991.32,
  "Кондензационни ТЕЦ": 596.58,
  "Топлофикационни ТЕЦ": 187.54,
  "Заводски ТЕЦ": 133.94,
  "ВЕЦ": 1017.93,
  "Малки ВЕЦ": 390.54,
  "ВяЕЦ": 89.87,
  "ФЕЦ": 0.0,
  "Био ЕЦ": 13.88,
  "Товар на РБ": 3763.02,
  "ССЕЕ_mw": -9.08,
  "ССЕЕ_state": "charging",
  "RO_mw": -2106.1,
  "SR_mw": -173.72,
  "MK_mw": 13.219999999999999,
  "GR_mw": 575.65,
  "TR_mw": 451.65999999999997,
  "gen_total_mw": 3421.6,
  "net_import_mw": -1239.3,
  "load_mw": 3763.0,
  "batt_charge_mw": 9.1,
  "batt_discharge_mw": 1559.2,
  "timestamp_utc": "2026-05-19T19:05:02Z",
  "date_bg": "2026-05-19"
}