{
  "АЕЦ": 980.98,
  "Кондензационни ТЕЦ": 515.84,
  "Топлофикационни ТЕЦ": 129.02,
  "Заводски ТЕЦ": 121.89,
  "ВЕЦ": 12.99,
  "Малки ВЕЦ": 195.16,
  "ВяЕЦ": 145.45,
  "ФЕЦ": 1716.74,
  "Био ЕЦ": 16.7,
  "Товар на РБ": 3794.58,
  "pumps_mw": 471.55,
  "ССЕЕ_mw": -1667.22,
  "ССЕЕ_state": "charging",
  "RO_mw": 1022.3299999999999,
  "SR_mw": 497.75,
  "MK_mw": 283.47999999999996,
  "GR_mw": 317.06,
  "TR_mw": -8.489999999999998,
  "gen_total_mw": 3834.8,
  "net_import_mw": 2112.1,
  "load_mw": 3794.6,
  "batt_charge_mw": 1676.8,
  "batt_discharge_mw": 9.6,
  "raw_gen_api": [
    [
      "АЕЦ 25,52%",
      980.98
    ],
    [
      "Кондензационни ТЕЦ 13,42%",
      515.84
    ],
    [
      "Топлофикационни ТЕЦ 3,36%",
      129.02
    ],
    [
      "Заводски ТЕЦ 3,17%",
      121.89
    ],
    [
      "ВЕЦ 0,34%",
      12.99
    ],
    [
      "Малки ВЕЦ 5,08%",
      195.16
    ],
    [
      "ВяЕЦ 3,78%",
      145.45
    ],
    [
      "ФЕЦ 44,66%",
      1716.74
    ],
    [
      "Био ЕЦ 0,43%",
      16.7
    ],
    [
      "ССЕБ - разреждане",
      "9.60"
    ],
    [
      "Товар на РБ",
      3794.58
    ],
    [
      "ССЕБ - зареждане",
      "1676.82"
    ],
    [
      "Помпи",
      "471.55"
    ]
  ],
  "timestamp_utc": "2026-06-13T09:55:03Z",
  "date_bg": "2026-06-13"
}