{
  "АЕЦ": 991.7,
  "Кондензационни ТЕЦ": 514.55,
  "Топлофикационни ТЕЦ": 167.66,
  "Заводски ТЕЦ": 105.97,
  "ВЕЦ": 57.93,
  "Малки ВЕЦ": 193.31,
  "ВяЕЦ": 170.05,
  "ФЕЦ": 1596.85,
  "Био ЕЦ": 17.69,
  "Товар на РБ": 3727.55,
  "ССЕЕ_mw": -1249.45,
  "ССЕЕ_state": "charging",
  "RO_mw": 961.0899999999999,
  "SR_mw": 124.21000000000001,
  "MK_mw": 107.6,
  "GR_mw": 151.49,
  "TR_mw": -155.47,
  "gen_total_mw": 3815.7,
  "net_import_mw": 1188.9,
  "load_mw": 3727.6,
  "batt_charge_mw": 1249.5,
  "batt_discharge_mw": 0.0,
  "timestamp_utc": "2026-05-24T08:20:02Z",
  "date_bg": "2026-05-24"
}