{
  "АЕЦ": 983.69,
  "Кондензационни ТЕЦ": 427.63,
  "Топлофикационни ТЕЦ": 146.21,
  "Заводски ТЕЦ": 126.83,
  "ВЕЦ": 610.97,
  "Малки ВЕЦ": 368.33,
  "ВяЕЦ": 20.84,
  "ФЕЦ": 0.0,
  "Био ЕЦ": 17.43,
  "Товар на РБ": 2880.76,
  "pumps_mw": 0.0,
  "ССЕЕ_mw": -0.11,
  "ССЕЕ_state": "charging",
  "RO_mw": -479.64,
  "SR_mw": -20.87,
  "MK_mw": -55.54,
  "GR_mw": 276.66999999999996,
  "TR_mw": 422.65999999999997,
  "gen_total_mw": 2701.9,
  "net_import_mw": 143.3,
  "load_mw": 2880.8,
  "batt_charge_mw": 2.7,
  "batt_discharge_mw": 2.6,
  "raw_gen_api": [
    [
      "АЕЦ 36,37%",
      983.69
    ],
    [
      "Кондензационни ТЕЦ 15,81%",
      427.63
    ],
    [
      "Топлофикационни ТЕЦ 5,41%",
      146.21
    ],
    [
      "Заводски ТЕЦ 4,69%",
      126.83
    ],
    [
      "ВЕЦ 22,59%",
      610.97
    ],
    [
      "Малки ВЕЦ 13,62%",
      368.33
    ],
    [
      "ВяЕЦ 0,77%",
      20.84
    ],
    [
      "ФЕЦ 0,00%",
      0
    ],
    [
      "Био ЕЦ 0,64%",
      17.43
    ],
    [
      "ССЕБ - разреждане",
      "2.57"
    ],
    [
      "Товар на РБ",
      2880.76
    ],
    [
      "ССЕБ - зареждане",
      "2.68"
    ],
    [
      "Помпи",
      "0.00"
    ]
  ],
  "timestamp_utc": "2026-06-05T23:55:03Z",
  "date_bg": "2026-06-06"
}