{
  "АЕЦ": 980.6,
  "Кондензационни ТЕЦ": 520.75,
  "Топлофикационни ТЕЦ": 128.27,
  "Заводски ТЕЦ": 123.35,
  "ВЕЦ": 84.44,
  "Малки ВЕЦ": 200.22,
  "ВяЕЦ": 48.4,
  "ФЕЦ": 1156.09,
  "Био ЕЦ": 17.48,
  "Товар на РБ": 3765.42,
  "pumps_mw": 187.14,
  "ССЕЕ_mw": -448.96,
  "ССЕЕ_state": "charging",
  "RO_mw": 662.5899999999999,
  "SR_mw": 401.47,
  "MK_mw": 154.22,
  "GR_mw": 86.11,
  "TR_mw": -183.41,
  "gen_total_mw": 3259.6,
  "net_import_mw": 1121.0,
  "load_mw": 3765.4,
  "batt_charge_mw": 479.0,
  "batt_discharge_mw": 30.1,
  "raw_gen_api": [
    [
      "АЕЦ 29,81%",
      980.6
    ],
    [
      "Кондензационни ТЕЦ 15,83%",
      520.75
    ],
    [
      "Топлофикационни ТЕЦ 3,90%",
      128.27
    ],
    [
      "Заводски ТЕЦ 3,75%",
      123.35
    ],
    [
      "ВЕЦ 2,57%",
      84.44
    ],
    [
      "Малки ВЕЦ 6,09%",
      200.22
    ],
    [
      "ВяЕЦ 1,47%",
      48.4
    ],
    [
      "ФЕЦ 35,14%",
      1156.09
    ],
    [
      "Био ЕЦ 0,53%",
      17.48
    ],
    [
      "ССЕБ - разреждане",
      "30.08"
    ],
    [
      "Товар на РБ",
      3765.42
    ],
    [
      "ССЕБ - зареждане",
      "479.04"
    ],
    [
      "Помпи",
      "187.14"
    ]
  ],
  "timestamp_utc": "2026-06-13T13:25:03Z",
  "date_bg": "2026-06-13"
}