{
  "АЕЦ": 982.92,
  "Кондензационни ТЕЦ": 404.85,
  "Топлофикационни ТЕЦ": 161.01,
  "Заводски ТЕЦ": 138.04,
  "ВЕЦ": 946.24,
  "Малки ВЕЦ": 384.86,
  "ВяЕЦ": 16.08,
  "ФЕЦ": 687.27,
  "Био ЕЦ": 13.02,
  "Товар на РБ": 3773.43,
  "pumps_mw": 0.0,
  "ССЕЕ_mw": 106.29,
  "ССЕЕ_state": "discharging",
  "RO_mw": -678.66,
  "SR_mw": -109.13,
  "MK_mw": -59.33,
  "GR_mw": 348.32000000000005,
  "TR_mw": 400.19,
  "gen_total_mw": 3734.3,
  "net_import_mw": -98.6,
  "load_mw": 3773.4,
  "batt_charge_mw": 35.5,
  "batt_discharge_mw": 141.8,
  "raw_gen_api": [
    [
      "АЕЦ 25,36%",
      982.92
    ],
    [
      "Кондензационни ТЕЦ 10,44%",
      404.85
    ],
    [
      "Топлофикационни ТЕЦ 4,15%",
      161.01
    ],
    [
      "Заводски ТЕЦ 3,56%",
      138.04
    ],
    [
      "ВЕЦ 24,41%",
      946.24
    ],
    [
      "Малки ВЕЦ 9,93%",
      384.86
    ],
    [
      "ВяЕЦ 0,41%",
      16.08
    ],
    [
      "ФЕЦ 17,73%",
      687.27
    ],
    [
      "Био ЕЦ 0,34%",
      13.02
    ],
    [
      "ССЕБ - разреждане",
      "141.77"
    ],
    [
      "Товар на РБ",
      3773.43
    ],
    [
      "ССЕБ - зареждане",
      "35.48"
    ],
    [
      "Помпи",
      "0.00"
    ]
  ],
  "timestamp_utc": "2026-06-04T16:05:03Z",
  "date_bg": "2026-06-04"
}