{
  "АЕЦ": 1987.59,
  "Кондензационни ТЕЦ": 371.38,
  "Топлофикационни ТЕЦ": 147.0,
  "Заводски ТЕЦ": 91.72,
  "ВЕЦ": 526.09,
  "Малки ВЕЦ": 298.3,
  "ВяЕЦ": 65.87,
  "ФЕЦ": 2286.56,
  "Био ЕЦ": 16.0,
  "Товар на РБ": 3765.65,
  "pumps_mw": 0.0,
  "ССЕЕ_mw": -37.18,
  "ССЕЕ_state": "charging",
  "RO_mw": -1568.37,
  "SR_mw": -587.2099999999999,
  "MK_mw": -230.26000000000002,
  "GR_mw": 138.41,
  "TR_mw": 249.45,
  "gen_total_mw": 5790.5,
  "net_import_mw": -1998.0,
  "load_mw": 3765.7,
  "batt_charge_mw": 46.3,
  "batt_discharge_mw": 9.1,
  "raw_gen_api": [
    [
      "АЕЦ 34,27%",
      1987.59
    ],
    [
      "Кондензационни ТЕЦ 6,40%",
      371.38
    ],
    [
      "Топлофикационни ТЕЦ 2,53%",
      147
    ],
    [
      "Заводски ТЕЦ 1,58%",
      91.72
    ],
    [
      "ВЕЦ 9,07%",
      526.09
    ],
    [
      "Малки ВЕЦ 5,14%",
      298.3
    ],
    [
      "ВяЕЦ 1,14%",
      65.87
    ],
    [
      "ФЕЦ 39,43%",
      2286.56
    ],
    [
      "Био ЕЦ 0,28%",
      16
    ],
    [
      "ССЕБ - разреждане",
      "9.12"
    ],
    [
      "Товар на РБ",
      3765.65
    ],
    [
      "ССЕБ - зареждане",
      "46.30"
    ],
    [
      "Помпи",
      "0.00"
    ]
  ],
  "timestamp_utc": "2026-06-19T05:35:03Z",
  "date_bg": "2026-06-19"
}