{
  "АЕЦ": 983.69,
  "Кондензационни ТЕЦ": 525.5,
  "Топлофикационни ТЕЦ": 134.85,
  "Заводски ТЕЦ": 120.2,
  "ВЕЦ": 109.58,
  "Малки ВЕЦ": 266.7,
  "ВяЕЦ": 56.26,
  "ФЕЦ": 1067.58,
  "Био ЕЦ": 16.07,
  "Товар на РБ": 3048.72,
  "pumps_mw": 0.0,
  "ССЕЕ_mw": -200.66,
  "ССЕЕ_state": "charging",
  "RO_mw": 32.81,
  "SR_mw": 121.39,
  "MK_mw": -110.68,
  "GR_mw": -183,
  "TR_mw": 112.7,
  "gen_total_mw": 3280.4,
  "net_import_mw": -26.8,
  "load_mw": 3048.7,
  "batt_charge_mw": 210.6,
  "batt_discharge_mw": 9.9,
  "raw_gen_api": [
    [
      "АЕЦ 29,90%",
      983.69
    ],
    [
      "Кондензационни ТЕЦ 15,97%",
      525.5
    ],
    [
      "Топлофикационни ТЕЦ 4,10%",
      134.85
    ],
    [
      "Заводски ТЕЦ 3,65%",
      120.2
    ],
    [
      "ВЕЦ 3,33%",
      109.58
    ],
    [
      "Малки ВЕЦ 8,11%",
      266.7
    ],
    [
      "ВяЕЦ 1,71%",
      56.26
    ],
    [
      "ФЕЦ 32,45%",
      1067.58
    ],
    [
      "Био ЕЦ 0,49%",
      16.07
    ],
    [
      "ССЕБ - разреждане",
      "9.93"
    ],
    [
      "Товар на РБ",
      3048.72
    ],
    [
      "ССЕБ - зареждане",
      "210.59"
    ],
    [
      "Помпи",
      "0.00"
    ]
  ],
  "timestamp_utc": "2026-06-14T04:50:03Z",
  "date_bg": "2026-06-14"
}