{
  "АЕЦ": 979.45,
  "Кондензационни ТЕЦ": 517.15,
  "Топлофикационни ТЕЦ": 143.24,
  "Заводски ТЕЦ": 126.57,
  "ВЕЦ": 377.0,
  "Малки ВЕЦ": 318.88,
  "ВяЕЦ": 217.99,
  "ФЕЦ": 1254.25,
  "Био ЕЦ": 12.47,
  "Товар на РБ": 3873.76,
  "pumps_mw": 0.0,
  "ССЕЕ_mw": -860.94,
  "ССЕЕ_state": "charging",
  "RO_mw": 708.2099999999999,
  "SR_mw": 96.69000000000001,
  "MK_mw": -43.09,
  "GR_mw": -154.52,
  "TR_mw": 158.74,
  "gen_total_mw": 3947.0,
  "net_import_mw": 766.0,
  "load_mw": 3873.8,
  "batt_charge_mw": 861.0,
  "batt_discharge_mw": 0.0,
  "raw_gen_api": [
    [
      "АЕЦ 24,81%",
      979.45
    ],
    [
      "Кондензационни ТЕЦ 13,10%",
      517.15
    ],
    [
      "Топлофикационни ТЕЦ 3,63%",
      143.24
    ],
    [
      "Заводски ТЕЦ 3,21%",
      126.57
    ],
    [
      "ВЕЦ 9,55%",
      377
    ],
    [
      "Малки ВЕЦ 8,08%",
      318.88
    ],
    [
      "ВяЕЦ 5,52%",
      217.99
    ],
    [
      "ФЕЦ 31,78%",
      1254.25
    ],
    [
      "Био ЕЦ 0,32%",
      12.47
    ],
    [
      "ССЕБ - разреждане",
      "0.03"
    ],
    [
      "Товар на РБ",
      3873.76
    ],
    [
      "ССЕБ - зареждане",
      "860.97"
    ],
    [
      "Помпи",
      "0.00"
    ]
  ],
  "timestamp_utc": "2026-06-12T14:00:03Z",
  "date_bg": "2026-06-12"
}