{
  "АЕЦ": 1976.53,
  "Кондензационни ТЕЦ": 373.96,
  "Топлофикационни ТЕЦ": 137.81,
  "Заводски ТЕЦ": 101.98,
  "ВЕЦ": 17.04,
  "Малки ВЕЦ": 224.8,
  "ВяЕЦ": 122.88,
  "ФЕЦ": 2925.24,
  "Био ЕЦ": 12.47,
  "Товар на РБ": 4212.87,
  "pumps_mw": 466.26,
  "ССЕЕ_mw": -1572.24,
  "ССЕЕ_state": "charging",
  "RO_mw": -424.79,
  "SR_mw": -249.72,
  "MK_mw": 171.51999999999998,
  "GR_mw": 567.85,
  "TR_mw": 267.57,
  "gen_total_mw": 5892.7,
  "net_import_mw": 332.4,
  "load_mw": 4212.9,
  "batt_charge_mw": 1586.4,
  "batt_discharge_mw": 14.1,
  "raw_gen_api": [
    [
      "АЕЦ 33,46%",
      1976.53
    ],
    [
      "Кондензационни ТЕЦ 6,33%",
      373.96
    ],
    [
      "Топлофикационни ТЕЦ 2,33%",
      137.81
    ],
    [
      "Заводски ТЕЦ 1,73%",
      101.98
    ],
    [
      "ВЕЦ 0,29%",
      17.04
    ],
    [
      "Малки ВЕЦ 3,81%",
      224.8
    ],
    [
      "ВяЕЦ 2,08%",
      122.88
    ],
    [
      "ФЕЦ 49,52%",
      2925.24
    ],
    [
      "Био ЕЦ 0,21%",
      12.47
    ],
    [
      "ССЕБ - разреждане",
      "14.14"
    ],
    [
      "Товар на РБ",
      4212.87
    ],
    [
      "ССЕБ - зареждане",
      "1586.38"
    ],
    [
      "Помпи",
      "466.26"
    ]
  ],
  "timestamp_utc": "2026-06-18T12:00:03Z",
  "date_bg": "2026-06-18"
}