{
  "АЕЦ": 984.45,
  "Кондензационни ТЕЦ": 450.16,
  "Топлофикационни ТЕЦ": 158.79,
  "Заводски ТЕЦ": 125.32,
  "ВЕЦ": 1045.89,
  "Малки ВЕЦ": 386.73,
  "ВяЕЦ": 105.01,
  "ФЕЦ": 0.0,
  "Био ЕЦ": 16.94,
  "Товар на РБ": 3416.11,
  "pumps_mw": 0.0,
  "ССЕЕ_mw": 1266.99,
  "ССЕЕ_state": "discharging",
  "RO_mw": -1564.81,
  "SR_mw": -351.57,
  "MK_mw": -84.93,
  "GR_mw": 492.93999999999994,
  "TR_mw": 347.26,
  "gen_total_mw": 3273.3,
  "net_import_mw": -1161.1,
  "load_mw": 3416.1,
  "batt_charge_mw": 0.5,
  "batt_discharge_mw": 1267.5,
  "timestamp_utc": "2026-06-03T20:00:03Z",
  "date_bg": "2026-06-03"
}