{
  "АЕЦ": 993.22,
  "Кондензационни ТЕЦ": 563.94,
  "Топлофикационни ТЕЦ": 165.35,
  "Заводски ТЕЦ": 123.36,
  "ВЕЦ": 67.45,
  "Малки ВЕЦ": 312.16,
  "ВяЕЦ": 504.26,
  "ФЕЦ": 0.0,
  "Био ЕЦ": 18.1,
  "Товар на РБ": 2889.98,
  "ССЕЕ_mw": -6.27,
  "ССЕЕ_state": "charging",
  "RO_mw": -656.76,
  "SR_mw": -142.44,
  "MK_mw": -28.72,
  "GR_mw": 466.09000000000003,
  "TR_mw": 497.21000000000004,
  "gen_total_mw": 2747.8,
  "net_import_mw": 135.4,
  "load_mw": 2890.0,
  "batt_charge_mw": 6.3,
  "batt_discharge_mw": 1.4,
  "timestamp_utc": "2026-05-21T01:05:03Z",
  "date_bg": "2026-05-21"
}