{
  "АЕЦ": 983.31,
  "Кондензационни ТЕЦ": 518.73,
  "Топлофикационни ТЕЦ": 134.52,
  "Заводски ТЕЦ": 121.81,
  "ВЕЦ": 11.98,
  "Малки ВЕЦ": 197.36,
  "ВяЕЦ": 38.61,
  "ФЕЦ": 1331.14,
  "Био ЕЦ": 17.07,
  "Товар на РБ": 3935.41,
  "pumps_mw": 469.91,
  "ССЕЕ_mw": -1170.34,
  "ССЕЕ_state": "charging",
  "RO_mw": 942.8,
  "SR_mw": 563.02,
  "MK_mw": 355.72,
  "GR_mw": 431.56,
  "TR_mw": -72.46000000000001,
  "gen_total_mw": 3354.5,
  "net_import_mw": 2220.6,
  "load_mw": 3935.4,
  "batt_charge_mw": 1187.1,
  "batt_discharge_mw": 16.8,
  "raw_gen_api": [
    [
      "АЕЦ 29,17%",
      983.31
    ],
    [
      "Кондензационни ТЕЦ 15,39%",
      518.73
    ],
    [
      "Топлофикационни ТЕЦ 3,99%",
      134.52
    ],
    [
      "Заводски ТЕЦ 3,61%",
      121.81
    ],
    [
      "ВЕЦ 0,36%",
      11.98
    ],
    [
      "Малки ВЕЦ 5,85%",
      197.36
    ],
    [
      "ВяЕЦ 1,15%",
      38.61
    ],
    [
      "ФЕЦ 39,48%",
      1331.14
    ],
    [
      "Био ЕЦ 0,51%",
      17.07
    ],
    [
      "ССЕБ - разреждане",
      "16.76"
    ],
    [
      "Товар на РБ",
      3935.41
    ],
    [
      "ССЕБ - зареждане",
      "1187.10"
    ],
    [
      "Помпи",
      "469.91"
    ]
  ],
  "timestamp_utc": "2026-06-13T12:30:02Z",
  "date_bg": "2026-06-13"
}