{
  "АЕЦ": 980.98,
  "Кондензационни ТЕЦ": 376.66,
  "Топлофикационни ТЕЦ": 139.15,
  "Заводски ТЕЦ": 98.69,
  "ВЕЦ": 370.11,
  "Малки ВЕЦ": 310.59,
  "ВяЕЦ": 26.94,
  "ФЕЦ": 2755.08,
  "Био ЕЦ": 12.73,
  "Товар на РБ": 3641.68,
  "pumps_mw": 0.0,
  "ССЕЕ_mw": 24.23,
  "ССЕЕ_state": "discharging",
  "RO_mw": -1018.6800000000001,
  "SR_mw": -564.32,
  "MK_mw": -171,
  "GR_mw": 76.77,
  "TR_mw": 216.74,
  "gen_total_mw": 5070.9,
  "net_import_mw": -1460.5,
  "load_mw": 3641.7,
  "batt_charge_mw": 131.5,
  "batt_discharge_mw": 155.7,
  "raw_gen_api": [
    [
      "АЕЦ 18,77%",
      980.98
    ],
    [
      "Кондензационни ТЕЦ 7,21%",
      376.66
    ],
    [
      "Топлофикационни ТЕЦ 2,66%",
      139.15
    ],
    [
      "Заводски ТЕЦ 1,89%",
      98.69
    ],
    [
      "ВЕЦ 7,08%",
      370.11
    ],
    [
      "Малки ВЕЦ 5,94%",
      310.59
    ],
    [
      "ВяЕЦ 0,52%",
      26.94
    ],
    [
      "ФЕЦ 52,71%",
      2755.08
    ],
    [
      "Био ЕЦ 0,24%",
      12.73
    ],
    [
      "ССЕБ - разреждане",
      "155.69"
    ],
    [
      "Товар на РБ",
      3641.68
    ],
    [
      "ССЕБ - зареждане",
      "131.46"
    ],
    [
      "Помпи",
      "0.00"
    ]
  ],
  "timestamp_utc": "2026-06-08T13:55:03Z",
  "date_bg": "2026-06-08"
}